nisync/__init__.py
nisync/_attributes.py
nisync/_errorcodes.py
nisync/_library.py
nisync/_library_singleton.py
nisync/_visatype.py
nisync/constants.py
nisync/enums.py
nisync/errors.py
nisync/session.py
nisync-0.2.dist-info/LICENSE
nisync-0.2.dist-info/METADATA
nisync-0.2.dist-info/WHEEL
nisync-0.2.dist-info/RECORD
