Metadata-Version: 2.1
Name: nisync
Version: 0.2
Summary: NI-Sync Python API
Home-page: https://github.com/ni/nisync-python
License: MIT
Author: NI
Author-email: opensource@ni.com
Maintainer: NI
Maintainer-email: opensource@ni.com
Requires-Python: >=3.8.1,<4.0.0
Classifier: Development Status :: 1 - Planning
Classifier: Intended Audience :: Developers
Classifier: Intended Audience :: Manufacturing
Classifier: Intended Audience :: Science/Research
Classifier: License :: OSI Approved :: MIT License
Classifier: Operating System :: Microsoft :: Windows
Classifier: Operating System :: POSIX :: Linux
Classifier: Programming Language :: Python :: 3
Classifier: Programming Language :: Python :: 3.9
Classifier: Programming Language :: Python :: 3.10
Classifier: Programming Language :: Python :: 3.11
Classifier: Programming Language :: Python :: 3.12
Classifier: Programming Language :: Python :: 3.13
Classifier: Programming Language :: Python :: 3.8
Classifier: Programming Language :: Python :: Implementation :: CPython
Classifier: Topic :: Scientific/Engineering
Classifier: Topic :: System :: Hardware
Requires-Dist: hightime
Project-URL: Repository, https://github.com/ni/nisync-python
